README.rst
setup.py
oamap/__init__.py
oamap/compiler.py
oamap/database.py
oamap/dataset.py
oamap/fill.py
oamap/fillable.py
oamap/generator.py
oamap/inference.py
oamap/operations.py
oamap/proxy.py
oamap/schema.py
oamap/util.py
oamap/version.py
oamap.egg-info/PKG-INFO
oamap.egg-info/SOURCES.txt
oamap.egg-info/dependency_links.txt
oamap.egg-info/requires.txt
oamap.egg-info/top_level.txt
oamap/backend/__init__.py
oamap/backend/arrow.py
oamap/backend/numpyfile.py
oamap/backend/packing.py
oamap/backend/root/__init__.py
oamap/backend/root/cmsnano.py
oamap/extension/__init__.py
oamap/extension/common.py